surround/__init__.py
surround/assembler.py
surround/config.py
surround/defaults.yaml
surround/project.py
surround/run_modes.py
surround/runners.py
surround/stage.py
surround/state.py
surround/surround.py
surround/util.py
surround-0.1.2.dist-info/METADATA
surround-0.1.2.dist-info/WHEEL
surround-0.1.2.dist-info/top_level.txt
surround-0.1.2.dist-info/RECORD
