Metadata-Version: 2.1
Name: surround
Version: 0.1.2
Summary: Surround is a framework for serving machine learning pipelines in Python.
Home-page: https://github.com/a2i2/surround
Author: Scott Barnett
Author-email: scott.barnett@deakin.edu.au
License: BSD-3-Clause License
Platform: UNKNOWN
Requires-Dist: pyaml (==17.12.1)
Requires-Dist: hydra-core (==1.0.5)
